README.md
setup.py
conveyor/__init__.py
conveyor/cell_conductor.py
conveyor/code_cell.py
conveyor/nbglobals.py
conveyor/nbresult.py
conveyor/notebook.py
conveyor/multinb/__init__.py
conveyor/multinb/pipeline_objects.py
conveyor/multinb/pipeline_simple.py
conveyor/multinb/plresult.py
jupyter_conveyor.egg-info/PKG-INFO
jupyter_conveyor.egg-info/SOURCES.txt
jupyter_conveyor.egg-info/dependency_links.txt
jupyter_conveyor.egg-info/requires.txt
jupyter_conveyor.egg-info/top_level.txt
test/__init__.py
test/test_notebook_timeout.py
test/test_pipeline.py
test/test_single_notebook.py