Metadata-Version: 2.1
Name: jupyter-conveyor
Version: 0.0.3
Summary: A toolset to accelerate Jupyter notebook workflows
Home-page: https://github.com/sidgarimella/conveyor
Author: Siddharth Garimella
Author-email: sidgarimella@outlook.com
License: MIT
Download-URL: https://github.com/sidgarimella/conveyor/archive/v_003.tar.gz
Platform: UNKNOWN
Classifier: Intended Audience :: Developers
Classifier: License :: OSI Approved :: MIT License
Classifier: Operating System :: OS Independent
Classifier: Programming Language :: Python :: 3.5
Classifier: Programming Language :: Python :: 3.6
Classifier: Programming Language :: Python :: 3.7
Requires-Python: >=3.5
